Metadata-Version: 2.1
Name: sweetviz
Version: 2.3.1
Summary: A pandas-based library to visualize and compare datasets.
Author-email: Francois Bertrand <fb@fbdesignpro.com>
License: MIT License
Project-URL: Homepage, https://github.com/fbdesignpro/sweetviz
Project-URL: Bug Tracker, https://github.com/fbdesignpro/sweetviz/issues
Project-URL: Discussions, https://github.com/fbdesignpro/sweetviz/discussions
Project-URL: Changelog, https://github.com/fbdesignpro/sweetviz/releases
Keywords: pandas,data-science,data-analysis,python,eda
Classifier: Programming Language :: Python :: 3
Classifier: Programming Language :: Python :: 3.7
Classifier: Programming Language :: Python :: 3.8
Classifier: Programming Language :: Python :: 3.9
Classifier: Programming Language :: Python :: 3.10
Classifier: Programming Language :: Python :: 3.11
Classifier: Intended Audience :: Developers
Classifier: Intended Audience :: Science/Research
Classifier: License :: OSI Approved :: MIT License
Classifier: Operating System :: OS Independent
Classifier: Development Status :: 5 - Production/Stable
Classifier: Topic :: Scientific/Engineering :: Visualization
Classifier: Topic :: Software Development :: Libraries :: Python Modules
Requires-Python: >=3.7
License-File: LICENSE
Requires-Dist: pandas!=1.0.0,!=1.0.1,!=1.0.2,>=0.25.3
Requires-Dist: numpy>=1.16.0
Requires-Dist: matplotlib>=3.1.3
Requires-Dist: tqdm>=4.43.0
Requires-Dist: scipy>=1.3.2
Requires-Dist: jinja2>=2.11.1
Requires-Dist: importlib_resources>=1.2.0
Requires-Dist: importlib_metadata; python_version < "3.8"
Provides-Extra: test
Requires-Dist: pytest>=6; extra == "test"
Requires-Dist: pytest-cov>=3; extra == "test"
Provides-Extra: dev
Requires-Dist: pytest>=6; extra == "dev"
Requires-Dist: pytest-cov>=3; extra == "dev"
Provides-Extra: docs
Requires-Dist: sphinx>=4.0; extra == "docs"
Requires-Dist: myst_parser>=0.13; extra == "docs"
Requires-Dist: sphinx_book_theme>=0.1.0; extra == "docs"
Requires-Dist: sphinx_copybutton; extra == "docs"
Requires-Dist: sphinx_autodoc_typehints; extra == "docs"
Requires-Dist: furo; extra == "docs"
